{
  "_fv": 15,
  "_type": "block",
  "definition": {
    "texture": "base_wire_add",
    "textureTop": "",
    "textureLeft": "",
    "textureFront": "",
    "textureRight": "",
    "textureBack": "",
    "renderType": 2,
    "customModelName": "base_wire_con_2_angle_down:default",
    "rotationMode": 4,
    "emissiveRendering": false,
    "displayFluidOverlay": false,
    "itemTexture": "",
    "particleTexture": "base_wire_add",
    "hasTransparency": true,
    "connectedSides": false,
    "transparencyType": "TRANSLUCENT",
    "mx": 0.0,
    "my": 0.0,
    "mz": 0.0,
    "Mx": 1.0,
    "My": 1.0,
    "Mz": 1.0,
    "name": "Base Wire Con 2 Angle Down",
    "specialInfo": [],
    "hardness": 1.0,
    "resistance": 10.0,
    "hasGravity": false,
    "isWaterloggable": true,
    "creativeTab": {
      "value": "No creative tab entry"
    },
    "destroyTool": "pickaxe",
    "customDrop": {
      "value": "CUSTOM:BaseWireCon0"
    },
    "dropAmount": 1,
    "useLootTableForDrops": false,
    "enchantPowerBonus": 0.0,
    "plantsGrowOn": false,
    "canProvidePower": false,
    "lightOpacity": 0,
    "material": {
      "value": "IRON"
    },
    "tickRate": 1,
    "tickRandomly": false,
    "isReplaceable": false,
    "colorOnMap": "DEFAULT",
    "creativePickItem": {
      "value": "CUSTOM:BaseWireCon0"
    },
    "offsetType": "NONE",
    "aiPathNodeType": "BLOCKED",
    "flammability": 0,
    "fireSpreadSpeed": 0,
    "isLadder": false,
    "slipperiness": 0.6,
    "reactionToPushing": "DESTROY",
    "isNotColidable": false,
    "soundOnStep": {
      "value": "METAL"
    },
    "luminance": 0,
    "unbreakable": false,
    "breakHarvestLevel": 0,
    "spawnParticles": false,
    "particleToSpawn": {
      "value": "EXPLOSION_NORMAL"
    },
    "particleSpawningShape": "Spread",
    "particleSpawningRadious": 0.5,
    "particleAmount": 4,
    "hasInventory": true,
    "guiBoundTo": "<NONE>",
    "openGUIOnRightClick": false,
    "inventorySize": 9,
    "inventoryStackSize": 64,
    "inventoryDropWhenDestroyed": true,
    "inventoryComparatorPower": true,
    "inventoryOutSlotIDs": [],
    "inventoryInSlotIDs": [],
    "hasEnergyStorage": true,
    "energyInitial": 0,
    "energyCapacity": 100000,
    "energyMaxReceive": 100000,
    "energyMaxExtract": 100000,
    "isFluidTank": false,
    "fluidCapacity": 8000,
    "fluidRestrictions": [],
    "onBlockAdded": {
      "name": "WirePlaced"
    },
    "onNeighbourBlockChanges": {
      "name": "WireConnector"
    },
    "onTickUpdate": {
      "name": "WireUpdateTick"
    },
    "spawnWorldTypes": [],
    "restrictionBiomes": [],
    "blocksToReplace": [
      {
        "value": "Blocks.STONE"
      }
    ],
    "frequencyPerChunks": 10,
    "frequencyOnChunk": 16,
    "minGenerateHeight": 0,
    "maxGenerateHeight": 64
  }
}